tuitoy/__init__.py
tuitoy/app.py
tuitoy/scenes.py
tuitoy/tuitoy.py
tuitoy/windows.py
TuiToy-0.0.4.dist-info/METADATA
TuiToy-0.0.4.dist-info/WHEEL
TuiToy-0.0.4.dist-info/top_level.txt
TuiToy-0.0.4.dist-info/RECORD
