Metadata-Version: 2.1
Name: TuiToy
Version: 0.0.4
Summary: A terminal user interface library for Python using curses under the hood.
Author-email: Austin Choi <austinch20@protonmail.com>
Project-URL: Homepage, https://github.com/choice404/TuiToy
Project-URL: Issues, https://github.com/choice404/TuiToy/issues
Classifier: Programming Language :: Python :: 3
Classifier: License :: OSI Approved :: MIT License
Classifier: Operating System :: OS Independent
Requires-Python: >=3.8
Requires-Dist: windows-curses ; platform_system == "Windows"
